finnish_name_generator/__init__.py
finnish_name_generator/py.typed
finnish_name_generator-0.2.1.dist-info/METADATA
finnish_name_generator-0.2.1.dist-info/WHEEL
finnish_name_generator-0.2.1.dist-info/RECORD
