Metadata-Version: 2.1
Name: finnish-name-generator
Version: 0.2.1
Summary: Generate random Finnish names
License: MIT
Author: Lassi Haasio
Requires-Python: >=3.10,<4.0
Classifier: License :: OSI Approved :: MIT License
Classifier: Programming Language :: Python :: 3
Classifier: Programming Language :: Python :: 3.10
Classifier: Programming Language :: Python :: 3.11
Classifier: Programming Language :: Python :: 3.12
